<?xml version="1.0" encoding="UTF-8"?>
<!--
To change this license header, choose License Headers in Project Properties.
To change this template file, choose Tools | Templates
and open the template in the editor.
-->

<directory type="year">
    <directory type="month">
        <directory type="folder" name="GIFs">
            <file>
                <fileProperty type="fileType">gif</fileProperty>
            </file>
        </directory>
        <directory type="audio" />
        <directory type="video" />
        <directory type="picture" />
        <directory type="document" />
        <directory type="folder" name="Other" />
    </directory>
</directory>